ngy/Magic_Request.py
ngy/Magic_Request_sav.py
ngy/Map_func.py
ngy/Request.py
ngy/Tiles.py
ngy/Tools.py
ngy/__init__.py
ngy/data/wmts.xml
ngy-1.0.0.dist-info/METADATA
ngy-1.0.0.dist-info/WHEEL
ngy-1.0.0.dist-info/entry_points.txt
ngy-1.0.0.dist-info/licenses/LICENSE
ngy-1.0.0.dist-info/RECORD
